{
  "nm": "Main Scene",
  "ddd": 0,
  "h": 500,
  "w": 500,
  "meta": { "g": "@lottiefiles/creator 1.47.1" },
  "layers": [
    {
      "ty": 4,
      "nm": "mateball-favicon-big",
      "sr": 1,
      "st": 0,
      "op": 70,
      "ip": 0,
      "hd": false,
      "ddd": 0,
      "bm": 0,
      "hasMask": false,
      "ao": 0,
      "ks": {
        "a": { "a": 0, "k": [255.9263515472412, 256.3788754940033] },
        "s": {
          "a": 1,
          "k": [
            {
              "o": { "x": 0.65, "y": 0 },
              "i": { "x": 0.36, "y": 1 },
              "s": [90.1178, 90.1178],
              "t": 0
            },
            {
              "o": { "x": 0.65, "y": 0 },
              "i": { "x": 0.36, "y": 1 },
              "s": [74.1178, 74.12],
              "t": 35
            },
            {
              "o": { "x": 0.65, "y": 0 },
              "i": { "x": 1, "y": 1 },
              "s": [90.1178, 90.1178],
              "t": 70
            },
            { "s": [79.1178, 79.12], "t": 95 }
          ]
        },
        "sk": { "a": 0, "k": 0 },
        "p": { "a": 0, "k": [249.9263515472412, 250.3788754940033] },
        "r": {
          "a": 1,
          "k": [
            { "o": { "x": 0.55, "y": 0.06 }, "i": { "x": 0.36, "y": 1 }, "s": [0], "t": 0 },
            { "o": { "x": 0.65, "y": 0 }, "i": { "x": 0.36, "y": 1 }, "s": [180], "t": 35 },
            { "s": [360], "t": 70 }
          ]
        },
        "sa": { "a": 0, "k": 0 },
        "o": { "a": 0, "k": 100 }
      },
      "shapes": [
        {
          "ty": "gr",
          "bm": 0,
          "hd": false,
          "nm": "Group 1",
          "it": [
            {
              "ty": "sh",
              "bm": 0,
              "hd": false,
              "nm": "Path 1",
              "d": 1,
              "ks": {
                "a": 0,
                "k": {
                  "c": true,
                  "i": [
                    [0, 0],
                    [0, -50.496999999999986],
                    [45.789000000000044, 0],
                    [14.214999999999975, 22.89699999999999],
                    [27.125, -0.0009999999999763531],
                    [0, 50.496999999999986],
                    [-45.78899999999999, 0],
                    [-14.21599999999998, -22.896000000000015],
                    [-27.123999999999967, 0]
                  ],
                  "o": [
                    [45.789000000000044, 0],
                    [0, 50.49799999999999],
                    [-26.878999999999962, -0.0010000000000331966],
                    [-14.188000000000017, 23.245000000000005],
                    [-45.78799999999998, -0.0009999999999763531],
                    [0, -50.496999999999986],
                    [26.87900000000002, 0],
                    [14.187999999999988, -23.244],
                    [0, 0]
                  ],
                  "v": [
                    [320.919, 157.99],
                    [400.55, 253.046],
                    [320.919, 348.103],
                    [257.064, 309.85],
                    [192.82, 348.734],
                    [113.191, 253.677],
                    [192.82, 158.621],
                    [256.676, 196.871],
                    [320.919, 157.99]
                  ]
                }
              }
            },
            {
              "ty": "sh",
              "bm": 0,
              "hd": false,
              "nm": "Path 2",
              "d": 1,
              "ks": {
                "a": 0,
                "k": {
                  "c": true,
                  "i": [
                    [0, 0],
                    [11.167000000000002, -15.74199999999999],
                    [-6.926000000000016, 0],
                    [-5.834000000000003, -23.09099999999998],
                    [0, 0],
                    [0, 0],
                    [0, 0],
                    [23.573999999999984, -0.0010000000000331966],
                    [4.536999999999978, 1.8129999999999882],
                    [-14.62299999999999, -0.0009999999999763531],
                    [-9.870000000000005, 25.673999999999978],
                    [0, 11.487000000000023],
                    [-3.1049999999999898, 10.21599999999998],
                    [22.317000000000007, 0]
                  ],
                  "o": [
                    [-17.00399999999999, 0],
                    [5.899000000000001, -3.326999999999998],
                    [20.825999999999993, 0],
                    [0, 0],
                    [0, 0],
                    [0, 0],
                    [-2.9410000000000025, 27.814999999999998],
                    [-5.03400000000002, 0],
                    [10.75, 11.978999999999985],
                    [22.479000000000013, -0.0009999999999763531],
                    [-3.2450000000000045, -10.41700000000003],
                    [0, -11.227000000000004],
                    [-9.958999999999975, -25.358000000000004],
                    [0, 0]
                  ],
                  "v": [
                    [192.82, 178.947],
                    [148.423, 204.19],
                    [167.817, 199.004],
                    [212.072, 238.92],
                    [183.34, 252.177],
                    [183.34, 252.226],
                    [213.711, 262.879],
                    [167.817, 312.196],
                    [153.401, 309.401],
                    [192.82, 328.407],
                    [246.286, 286.129],
                    [241.29, 253.046],
                    [246.069, 220.669],
                    [192.82, 178.947]
                  ]
                }
              }
            },
            {
              "ty": "sh",
              "bm": 0,
              "hd": false,
              "nm": "Path 3",
              "d": 1,
              "ks": {
                "a": 0,
                "k": {
                  "c": true,
                  "i": [
                    [0, 0],
                    [11.185000000000002, -16.686000000000007],
                    [-7.562000000000012, 0],
                    [-5.83299999999997, -23.09099999999998],
                    [0, 0],
                    [0, 0],
                    [0, 0],
                    [23.57299999999998, 0],
                    [4.510000000000048, 1.7889999999999873],
                    [-14.34899999999999, -0.0010000000000331966],
                    [0, 43.273000000000025],
                    [30.942000000000007, 0]
                  ],
                  "o": [
                    [-17.567000000000007, 0],
                    [6.302999999999997, -3.9240000000000066],
                    [20.825999999999965, 0],
                    [0, 0],
                    [0, 0],
                    [0, 0],
                    [-2.9399999999999977, 27.814999999999998],
                    [-5, 0],
                    [10.668000000000006, 11.571000000000026],
                    [30.942000000000007, 0],
                    [0, -43.272999999999996],
                    [0, 0]
                  ],
                  "v": [
                    [320.919, 178.316],
                    [275.431, 205.142],
                    [296.434, 199.004],
                    [340.688, 238.92],
                    [311.957, 252.177],
                    [311.957, 252.226],
                    [342.327, 262.879],
                    [296.434, 312.196],
                    [282.109, 309.438],
                    [320.919, 327.776],
                    [380.224, 253.046],
                    [320.919, 178.316]
                  ]
                }
              }
            },
            {
              "ty": "fl",
              "bm": 0,
              "hd": false,
              "nm": "Fill",
              "c": { "a": 0, "k": [0.0706, 0.3882, 1] },
              "r": 1,
              "o": { "a": 0, "k": 100 }
            },
            {
              "ty": "tr",
              "a": { "a": 0, "k": [0, 0] },
              "s": { "a": 0, "k": [100, 100] },
              "sk": { "a": 0, "k": 0 },
              "p": { "a": 0, "k": [0, 0] },
              "r": { "a": 0, "k": 0 },
              "sa": { "a": 0, "k": 0 },
              "o": { "a": 0, "k": 100 }
            }
          ]
        },
        {
          "ty": "gr",
          "bm": 0,
          "hd": false,
          "nm": "Group 2",
          "it": [
            {
              "ty": "sh",
              "bm": 0,
              "hd": false,
              "nm": "Path 4",
              "d": 1,
              "ks": {
                "a": 0,
                "k": {
                  "c": true,
                  "i": [
                    [0, 0],
                    [5.159999999999968, -9.222610000000001],
                    [0, 0],
                    [0, -79.48999999999998],
                    [0, 0],
                    [98.89300000000003, -18.744000000000028],
                    [0, 0],
                    [-5.149000000000001, 9.204999999999984],
                    [0, 0],
                    [0.5001999999999995, 78.97199999999998],
                    [0, 0],
                    [-98.6, 19.4082],
                    [-0.5800000000000125, 0.15759999999999508],
                    [0, 0]
                  ],
                  "o": [
                    [10.197999999999979, -2.77185],
                    [0, 0],
                    [64.209, 37.10459999999999],
                    [0, 0],
                    [-0.6599999999999682, 104.19099999999997],
                    [0, 0],
                    [-10.188000000000017, 2.7299999999999613],
                    [0, 0],
                    [-63.918400000000005, -36.867999999999995],
                    [0, 0],
                    [0, -104.28999999999996],
                    [0.5209999999999866, -0.21750000000000114],
                    [0, 0],
                    [0, 0]
                  ],
                  "v": [
                    [378.817, 1.43965],
                    [392.353, 18.7707],
                    [363.176, 70.9244],
                    [470.591, 256.917],
                    [470.587, 258.305],
                    [296.145, 467.819],
                    [133.806, 511.329],
                    [120.31, 493.988],
                    [148.829, 442.998],
                    [41.266, 258.305],
                    [41.2617, 256.917],
                    [214.232, 46.2982],
                    [215.883, 45.7338],
                    [378.817, 1.43965]
                  ]
                }
              }
            },
            {
              "ty": "sh",
              "bm": 0,
              "hd": false,
              "nm": "Path 5",
              "d": 1,
              "ks": {
                "a": 0,
                "k": {
                  "c": true,
                  "i": [
                    [0, 0],
                    [0, -93.85699999999997],
                    [-93.857, 0],
                    [-0.0009999999999763531, 93.85700000000003],
                    [93.85600000000002, 0.00010000000000331966]
                  ],
                  "o": [
                    [-93.857, 0],
                    [0.0000999999999891088, 93.85700000000003],
                    [93.85600000000002, 0],
                    [0, -93.85699999999997],
                    [0, 0]
                  ],
                  "v": [
                    [255.927, 86.9739],
                    [85.9835, 256.917],
                    [255.927, 426.86],
                    [425.87, 256.917],
                    [255.927, 86.9739]
                  ]
                }
              }
            },
            {
              "ty": "fl",
              "bm": 0,
              "hd": false,
              "nm": "Fill",
              "c": { "a": 0, "k": [0.0706, 0.3882, 1] },
              "r": 1,
              "o": { "a": 0, "k": 100 }
            },
            {
              "ty": "tr",
              "a": { "a": 0, "k": [0, 0] },
              "s": { "a": 0, "k": [100, 100] },
              "sk": { "a": 0, "k": 0 },
              "p": { "a": 0, "k": [0, 0] },
              "r": { "a": 0, "k": 0 },
              "sa": { "a": 0, "k": 0 },
              "o": { "a": 0, "k": 100 }
            }
          ]
        }
      ],
      "ind": 1
    }
  ],
  "v": "5.7.0",
  "fr": 30,
  "op": 70,
  "ip": 0,
  "assets": []
}
